briefcase/__init__.py
briefcase/__main__.py
briefcase/cmdline.py
briefcase/config.py
briefcase/console.py
briefcase/constants.py
briefcase/exceptions.py
briefcase/bootstraps/__init__.py
briefcase/bootstraps/base.py
briefcase/bootstraps/console.py
briefcase/bootstraps/empty.py
briefcase/bootstraps/pygame.py
briefcase/bootstraps/pyside6.py
briefcase/bootstraps/toga.py
briefcase/commands/__init__.py
briefcase/commands/base.py
briefcase/commands/build.py
briefcase/commands/convert.py
briefcase/commands/create.py
briefcase/commands/dev.py
briefcase/commands/new.py
briefcase/commands/open.py
briefcase/commands/package.py
briefcase/commands/publish.py
briefcase/commands/run.py
briefcase/commands/update.py
briefcase/commands/upgrade.py
briefcase/integrations/__init__.py
briefcase/integrations/android_sdk.py
briefcase/integrations/base.py
briefcase/integrations/cookiecutter.py
briefcase/integrations/docker.py
briefcase/integrations/file.py
briefcase/integrations/flatpak.py
briefcase/integrations/git.py
briefcase/integrations/java.py
briefcase/integrations/linuxdeploy.py
briefcase/integrations/rcedit.py
briefcase/integrations/subprocess.py
briefcase/integrations/visualstudio.py
briefcase/integrations/windows_sdk.py
briefcase/integrations/wix.py
briefcase/integrations/xcode.py
briefcase/platforms/__init__.py
briefcase/platforms/android/__init__.py
briefcase/platforms/android/gradle.py
briefcase/platforms/iOS/__init__.py
briefcase/platforms/iOS/xcode.py
briefcase/platforms/linux/__init__.py
briefcase/platforms/linux/appimage.py
briefcase/platforms/linux/flatpak.py
briefcase/platforms/linux/snap.py
briefcase/platforms/linux/system.py
briefcase/platforms/macOS/__init__.py
briefcase/platforms/macOS/app.py
briefcase/platforms/macOS/filters.py
briefcase/platforms/macOS/utils.py
briefcase/platforms/macOS/xcode.py
briefcase/platforms/tvOS/__init__.py
briefcase/platforms/tvOS/xcode.py
briefcase/platforms/watchOS/__init__.py
briefcase/platforms/watchOS/xcode.py
briefcase-0.3.24.dist-info/licenses/LICENSE
briefcase-0.3.24.dist-info/METADATA
briefcase-0.3.24.dist-info/WHEEL
briefcase-0.3.24.dist-info/entry_points.txt
briefcase-0.3.24.dist-info/top_level.txt
briefcase-0.3.24.dist-info/RECORD
