Metadata-Version: 2.4
Name: briefcase
Version: 0.3.24
Summary: Tools to support converting a Python project into a standalone native application.
Author-email: Russell Keith-Magee <russell@keith-magee.com>
Maintainer-email: BeeWare Team <team@beeware.org>
License-Expression: BSD-3-Clause
Project-URL: Homepage, https://beeware.org/briefcase
Project-URL: Funding, https://beeware.org/contributing/membership/
Project-URL: Documentation, https://briefcase.readthedocs.io/en/latest/
Project-URL: Tracker, https://github.com/beeware/briefcase/issues
Project-URL: Source, https://github.com/beeware/briefcase
Keywords: app,packaging,installer,macOS,iOS,android,mobile,windows,linux,flatpak,appimage,deb,rpm,pkg,tvOS,watch,watchOS,wearos,web,pyscript,pyodide
Classifier: Development Status :: 4 - Beta
Classifier: Intended Audience :: Developers
Classifier: Operating System :: OS Independent
Classifier: Programming Language :: Python :: 3
Classifier: Programming Language :: Python :: 3.9
Classifier: Programming Language :: Python :: 3.10
Classifier: Programming Language :: Python :: 3.11
Classifier: Programming Language :: Python :: 3.12
Classifier: Programming Language :: Python :: 3.13
Classifier: Programming Language :: Python :: 3 :: Only
Classifier: Topic :: Software Development
Classifier: Topic :: Utilities
Requires-Python: >=3.9
License-File: LICENSE
Requires-Dist: importlib_metadata>=4.4; python_version <= "3.9"
Requires-Dist: packaging>=24.2
Requires-Dist: pip>=24.3
Requires-Dist: setuptools>=60
Requires-Dist: wheel>=0.37
Requires-Dist: build>=0.10
Requires-Dist: truststore>=0.10.1; python_version >= "3.10"
Requires-Dist: cookiecutter<3.0,>=2.6.0
Requires-Dist: dmgbuild<2.0,>=1.6.4; sys_platform == "darwin"
Requires-Dist: GitPython<4.0,>=3.1
Requires-Dist: platformdirs<5.0,>=2.6
Requires-Dist: psutil<8.0,>=5.9
Requires-Dist: python-dateutil>=2.9.0.post0
Requires-Dist: httpx<1.0,>=0.20
Requires-Dist: rich<15.0,>=12.6
Requires-Dist: tomli<3.0,>=2.0; python_version <= "3.10"
Requires-Dist: tomli_w<2.0,>=1.0
Provides-Extra: dev
Requires-Dist: coverage[toml]==7.9.2; extra == "dev"
Requires-Dist: coverage-conditional-plugin==0.9.0; extra == "dev"
Requires-Dist: pre-commit==4.2.0; extra == "dev"
Requires-Dist: pytest==8.4.1; extra == "dev"
Requires-Dist: pytest-xdist==3.8.0; extra == "dev"
Requires-Dist: setuptools_scm==8.3.1; extra == "dev"
Requires-Dist: tox==4.27.0; extra == "dev"
Provides-Extra: docs
Requires-Dist: furo==2024.8.6; extra == "docs"
Requires-Dist: pyenchant==3.2.2; extra == "docs"
Requires-Dist: sphinx==8.2.3; extra == "docs"
Requires-Dist: sphinx_tabs==3.4.7; extra == "docs"
Requires-Dist: sphinx-autobuild==2024.10.3; extra == "docs"
Requires-Dist: sphinx-copybutton==0.5.2; extra == "docs"
Requires-Dist: sphinxcontrib-spelling==8.0.1; extra == "docs"
Dynamic: license-file
